parakh_num_rev/__init__.py
parakh_string_repl/__init__.py
parakh_basic_string_pkgs-0.1.dist-info/METADATA
parakh_basic_string_pkgs-0.1.dist-info/WHEEL
parakh_basic_string_pkgs-0.1.dist-info/top_level.txt
parakh_basic_string_pkgs-0.1.dist-info/RECORD
